pydeep.cpython-38-aarch64-linux-gnu.so
pydeep2.libs/libfuzzy-32a10928.so.2.1.0
pydeep2-0.5.dist-info/RECORD
pydeep2-0.5.dist-info/top_level.txt
pydeep2-0.5.dist-info/METADATA
pydeep2-0.5.dist-info/WHEEL
pydeep2-0.5.dist-info/LICENSE
