Metadata-Version: 2.1
Name: pydeep2
Version: 0.5
Summary: Python bindings for ssdeep
Home-page: https://www.github.com/JakubOnderka/pydeep
Author: Kiran Bandla
Author-email: kbandla@in2void.com
License: BSD
Platform: UNKNOWN
License-File: LICENSE
